.gitignore
LICENSE.txt
README.rst
fuse.py
hfive2mat.py
plot_h5_timestamps.py
plot_raw_timeseries.py
setup.py
strokelitude/__init__.py
strokelitude/data_format.py
strokelitude/plot_latencies.py
strokelitude/plugin.py
strokelitude/strokelitude.py
strokelitude.egg-info/PKG-INFO
strokelitude.egg-info/SOURCES.txt
strokelitude.egg-info/dependency_links.txt
strokelitude.egg-info/entry_points.txt
strokelitude.egg-info/top_level.txt
strokelitude.egg-info/zip-safe