Metadata-Version: 1.0
Name: strokelitude
Version: 0.3
Summary: realtime wingstroke amplitude analyzer (fview plugin)
Home-page: UNKNOWN
Author: Andrew Straw
Author-email: strawman@astraw.com
License: UNKNOWN
Platform: UNKNOWN
